requests_download.py
requests_download-0.1.2.dist-info/LICENSE
requests_download-0.1.2.dist-info/WHEEL
requests_download-0.1.2.dist-info/METADATA
requests_download-0.1.2.dist-info/RECORD
